pytello/__init__.py
pytello/main.py
pytello-3.0.0.dist-info/LICENSE
pytello-3.0.0.dist-info/METADATA
pytello-3.0.0.dist-info/WHEEL
pytello-3.0.0.dist-info/top_level.txt
pytello-3.0.0.dist-info/RECORD
