Metadata-Version: 2.1
Name: pytello
Version: 3.0.0
Summary: A package to make it easier to fly your tello drone in python
Home-page: https://github.com/Suave101/Py-Tello
Author: Alexander Doyle
Author-email: alexanderthegreat2025@gmail.com
Project-URL: Documentation, https://github.com/Suave101/Py-Tello/blob/master/Py-tello%203.0/readme.md
Classifier: Programming Language :: Python :: 3
Classifier: License :: OSI Approved :: MIT License
Classifier: Operating System :: OS Independent
Requires-Python: >=3.0
License-File: LICENSE
